uv_packsize/__init__.py
uv_packsize/__main__.py
uv_packsize/cli.py
uv_packsize-0.1.1.dist-info/licenses/LICENSE
uv_packsize-0.1.1.dist-info/METADATA
uv_packsize-0.1.1.dist-info/WHEEL
uv_packsize-0.1.1.dist-info/entry_points.txt
uv_packsize-0.1.1.dist-info/top_level.txt
uv_packsize-0.1.1.dist-info/RECORD
