Metadata-Version: 2.4
Name: uv-packsize
Version: 0.1.1
Summary: report size of python package with its deps using uv
Author: kj-9
License-Expression: Apache-2.0
Project-URL: Homepage, https://github.com/kj-9/uv-packsize
Project-URL: Changelog, https://github.com/kj-9/uv-packsize/releases
Project-URL: Issues, https://github.com/kj-9/uv-packsize/issues
Project-URL: CI, https://github.com/kj-9/uv-packsize/actions
Requires-Python: >=3.9
License-File: LICENSE
Requires-Dist: click
Dynamic: license-file
